CommandToDomoticz/CommandToDomoticz.py
CommandToDomoticz/__init__.py
CommandToDomoticz-0.9.4.dist-info/METADATA
CommandToDomoticz-0.9.4.dist-info/RECORD
CommandToDomoticz-0.9.4.dist-info/WHEEL
CommandToDomoticz-0.9.4.dist-info/top_level.txt
